attackctl/__init__.py
attackctl/cli.py
attackctl/data.py
attackctl/display.py
attackctl/models.py
attackctl/rules.py
attackctl/search.py
mitre_attackctl-1.1.0.dist-info/licenses/LICENSE
mitre_attackctl-1.1.0.dist-info/METADATA
mitre_attackctl-1.1.0.dist-info/WHEEL
mitre_attackctl-1.1.0.dist-info/entry_points.txt
mitre_attackctl-1.1.0.dist-info/top_level.txt
mitre_attackctl-1.1.0.dist-info/RECORD
