Metadata-Version: 2.4
Name: mitre-attackctl
Version: 1.1.0
Summary: A fast, batteries-included CLI companion for MITRE ATT&CK® TTPs
Author-email: Jonathan Haas <jonathan@haasonsaas.com>
Maintainer-email: Jonathan Haas <jonathan@haasonsaas.com>
License-Expression: MIT
Project-URL: Homepage, https://github.com/haasonsaas/mitre-attackctl
Project-URL: Repository, https://github.com/haasonsaas/mitre-attackctl
Project-URL: Issues, https://github.com/haasonsaas/mitre-attackctl/issues
Project-URL: Documentation, https://github.com/haasonsaas/mitre-attackctl#readme
Project-URL: Changelog, https://github.com/haasonsaas/mitre-attackctl/blob/main/CHANGELOG.md
Keywords: mitre,attack,ttps,cybersecurity,cli,threat-hunting,security,blue-team
Classifier: Development Status :: 4 - Beta
Classifier: Environment :: Console
Classifier: Intended Audience :: Information Technology
Classifier: Intended Audience :: System Administrators
Classifier: Operating System :: OS Independent
Classifier: Programming Language :: Python :: 3
Classifier: Programming Language :: Python :: 3.9
Classifier: Programming Language :: Python :: 3.10
Classifier: Programming Language :: Python :: 3.11
Classifier: Programming Language :: Python :: 3.12
Classifier: Programming Language :: Python :: 3.13
Classifier: Topic :: Security
Classifier: Topic :: System :: Systems Administration
Classifier: Topic :: Utilities
Classifier: Typing :: Typed
Requires-Python: >=3.9
License-File: LICENSE
Requires-Dist: typer[all]>=0.9.0
Requires-Dist: rich>=13.0.0
Requires-Dist: rapidfuzz>=3.0.0
Requires-Dist: requests>=2.31.0
Requires-Dist: stix2>=3.0.0
Requires-Dist: taxii2-client>=2.3.0
Requires-Dist: pydantic>=2.0.0
Requires-Dist: jinja2>=3.1.0
Requires-Dist: pyyaml>=6.0.0
Requires-Dist: click>=8.1.0
Provides-Extra: dev
Requires-Dist: pytest>=7.0.0; extra == "dev"
Requires-Dist: pytest-cov>=4.0.0; extra == "dev"
Requires-Dist: black>=23.0.0; extra == "dev"
Requires-Dist: ruff>=0.1.0; extra == "dev"
Requires-Dist: mypy>=1.0.0; extra == "dev"
Requires-Dist: pre-commit>=3.0.0; extra == "dev"
Provides-Extra: ai
Requires-Dist: openai>=1.0.0; extra == "ai"
Dynamic: license-file
